{"v":5,"entries":{"examples-all--simple-paragraph":{"type":"story","id":"examples-all--simple-paragraph","name":"Simple Paragraph","title":"Examples/All","importPath":"./src/stories/Compare.stories.tsx","tags":["dev","test"]},"examples-all--complex-paragraph":{"type":"story","id":"examples-all--complex-paragraph","name":"Complex Paragraph","title":"Examples/All","importPath":"./src/stories/Compare.stories.tsx","tags":["dev","test"]},"examples-all--array":{"type":"story","id":"examples-all--array","name":"Array","title":"Examples/All","importPath":"./src/stories/Compare.stories.tsx","tags":["dev","test"]},"examples-all--disordered":{"type":"story","id":"examples-all--disordered","name":"Disordered","title":"Examples/All","importPath":"./src/stories/Compare.stories.tsx","tags":["dev","test"]},"examples-all--case-insensitive":{"type":"story","id":"examples-all--case-insensitive","name":"Case Insensitive","title":"Examples/All","importPath":"./src/stories/Compare.stories.tsx","tags":["dev","test"]},"examples-all--order-insensitive":{"type":"story","id":"examples-all--order-insensitive","name":"Order Insensitive","title":"Examples/All","importPath":"./src/stories/Compare.stories.tsx","tags":["dev","test"]},"compare-contentful-rich-text--docs":{"id":"compare-contentful-rich-text--docs","title":"Compare/Contentful Rich Text","name":"Docs","importPath":"./src/stories/ContentfulCompare.stories.tsx","type":"docs","tags":["dev","test","autodocs"],"storiesImports":[]},"compare-contentful-rich-text--contentful-text-mode":{"type":"story","id":"compare-contentful-rich-text--contentful-text-mode","name":"Contentful Text Mode","title":"Compare/Contentful Rich Text","importPath":"./src/stories/ContentfulCompare.stories.tsx","componentPath":"./src/components/Compare.tsx","tags":["dev","test","autodocs"]},"compare-contentful-rich-text--contentful-structure-mode":{"type":"story","id":"compare-contentful-rich-text--contentful-structure-mode","name":"Contentful Structure Mode","title":"Compare/Contentful Rich Text","importPath":"./src/stories/ContentfulCompare.stories.tsx","componentPath":"./src/components/Compare.tsx","tags":["dev","test","autodocs"]},"compare-contentful-rich-text--contentful-inline-view":{"type":"story","id":"compare-contentful-rich-text--contentful-inline-view","name":"Contentful Inline View","title":"Compare/Contentful Rich Text","importPath":"./src/stories/ContentfulCompare.stories.tsx","componentPath":"./src/components/Compare.tsx","tags":["dev","test","autodocs"]}}}